ojitos369_mysql_db/__init__.py
ojitos369_mysql_db/mysql_db.py
ojitos369_mysql_db-3.0.0.dist-info/licenses/LICENSE.txt
ojitos369_mysql_db-3.0.0.dist-info/METADATA
ojitos369_mysql_db-3.0.0.dist-info/WHEEL
ojitos369_mysql_db-3.0.0.dist-info/top_level.txt
ojitos369_mysql_db-3.0.0.dist-info/RECORD
