Metadata-Version: 2.4
Name: ojitos369_mysql_db
Version: 3.0.0
Summary: Funciones con conexiones a bases de datos
Home-page: https://github.com/Ojitos369/ojitos369-pip
Author: Ojitos369
Author-email: Ojitos369 <ojitos369@gmail.com>
License: LGPL v3
Project-URL: Homepage, https://github.com/Ojitos369/ojitos369-pip
Keywords: Utilidades,ojitos369,postgres
Classifier: Programming Language :: Python :: 3.8
Classifier: Programming Language :: Python :: 3.9
Classifier: Programming Language :: Python :: 3.10
Classifier: Programming Language :: Python :: 3.11
Classifier: Programming Language :: Python :: 3.12
Requires-Python: >=3.8
License-File: LICENSE.txt
Requires-Dist: mysql-connector-python
Requires-Dist: ojitos369
Requires-Dist: pandas
Dynamic: author
Dynamic: home-page
Dynamic: license-file
